basicmath
