Metadata-Version: 1.1
Name: basicmathfunctions
Version: 0.0.51
Summary: Basic math functions
Home-page: UNKNOWN
Author: Isaac Cobb
Author-email: cobbcoding@gmail.com
License: MIT
Keywords: math
Platform: UNKNOWN
Classifier: Development Status :: 5 - Production/Stable
Classifier: Intended Audience :: Education
Classifier: Operating System :: Microsoft :: Windows :: Windows 10
Classifier: License :: OSI Approved :: MIT License
Classifier: Programming Language :: Python :: 3
